[1,["9cB81AXOFHYJ6z97J/m21/"],0,[["sp.SkeletonData",["_name","_atlasText","textureNames","_skeletonJson","textures"],-1,3]],[[0,0,1,2,3,4,5]],[[0,"debuff","\ndebuff.png\nsize: 141,141\nformat: RGBA8888\nfilter: Linear,Linear\nrepeat: none\n晕眩\n  rotate: false\n  xy: 2, 2\n  size: 54, 39\n  orig: 54, 39\n  offset: 0, 0\n  index: -1\n晕眩ef\n  rotate: false\n  xy: 2, 43\n  size: 96, 96\n  orig: 96, 96\n  offset: 0, 0\n  index: -1\n",["debuff.png"],{"skeleton":{"hash":"2tZjiniRD+YENfbBYaj68orH/OI","spine":"3.6.53","width":96,"height":96,"images":"./images/"},"bones":[{"name":"root"},{"name":"y","parent":"root","length":20.76,"rotation":45,"scaleX":2.759,"scaleY":2.759},{"name":"晕眩1","parent":"root","length":34.65},{"name":"晕眩2","parent":"root","length":34.65},{"name":"晕眩ADD","parent":"root","length":34.65},{"name":"晕眩ef","parent":"root"}],"slots":[{"name":"y","bone":"y","attachment":"y"},{"name":"晕眩ef","bone":"晕眩ef","dark":"000000","attachment":"晕眩ef"},{"name":"晕眩efAD","bone":"晕眩ef","dark":"000000","attachment":"晕眩ef","blend":"additive"},{"name":"晕眩1","bone":"晕眩1","attachment":"晕眩"},{"name":"晕眩2","bone":"晕眩2","attachment":"晕眩"},{"name":"晕眩ADD","bone":"晕眩ADD","attachment":"晕眩","blend":"additive"}],"skins":{"default":{"y":{"y":{"type":"clipping","end":"晕眩efAD","vertexCount":4,"color":"ce3a3aff","vertices":[16.03,15.85,-15.54,16.01,-16.21,-15.86,15.77,-15.87]}},"晕眩1":{"晕眩":{"width":54,"height":39}},"晕眩2":{"晕眩":{"width":54,"height":39}},"晕眩ADD":{"晕眩":{"width":54,"height":39}},"晕眩ef":{"晕眩ef":{"width":96,"height":96}},"晕眩efAD":{"晕眩ef":{"width":96,"height":96}}}},"animations":{"in":{"slots":{"晕眩1":{"color":[{"time":0,"color":"ffffff00"},{"time":0.1667,"color":"ffffffff"}]},"晕眩2":{"color":[{"time":0,"color":"ffffff00"},{"time":0.1667,"color":"ffffffff"}]},"晕眩ADD":{"color":[{"time":0,"color":"ffffffff","curve":"stepped"},{"time":0.1667,"color":"ffffffff"},{"time":0.6667,"color":"ffffff00"}],"attachment":[{"time":0,"name":null},{"time":0.1667,"name":"晕眩"}]},"晕眩ef":{"twoColor":[{"time":0,"light":"ffffffff","dark":"000000","curve":"stepped"},{"time":0.1667,"light":"ffffffff","dark":"000000"},{"time":0.2333,"light":"ffffffff","dark":"ffc200"},{"time":0.8333,"light":"ffffffff","dark":"000000"}]},"晕眩efAD":{"twoColor":[{"time":0,"light":"ffffffff","dark":"000000","curve":"stepped"},{"time":0.1667,"light":"ffffffff","dark":"000000"},{"time":0.2333,"light":"ffffffff","dark":"ffc200"},{"time":0.8333,"light":"ffffffff","dark":"000000"}]}},"bones":{"晕眩1":{"rotate":[{"time":0,"angle":0}],"translate":[{"time":0,"x":-75,"y":0},{"time":0.1667,"x":0,"y":0,"curve":"stepped"},{"time":1,"x":0,"y":0}],"scale":[{"time":0,"x":1,"y":1}]},"晕眩2":{"rotate":[{"time":0,"angle":0}],"translate":[{"time":0,"x":75,"y":0},{"time":0.1667,"x":0,"y":0}],"scale":[{"time":0,"x":1,"y":1}]},"晕眩ADD":{"rotate":[{"time":0,"angle":0,"curve":"stepped"},{"time":0.1667,"angle":0}],"translate":[{"time":0,"x":0,"y":0,"curve":"stepped"},{"time":0.1667,"x":0,"y":0}],"scale":[{"time":0,"x":1,"y":1,"curve":"stepped"},{"time":0.1667,"x":1,"y":1,"curve":[0.25,0,0.75,1]},{"time":0.6667,"x":1.339,"y":1.339}]},"y":{"rotate":[{"time":0,"angle":0}],"translate":[{"time":0,"x":0,"y":0}],"scale":[{"time":0,"x":0.034,"y":0.034,"curve":"stepped"},{"time":0.1667,"x":0.034,"y":0.034,"curve":[0.25,0,0.75,1]},{"time":0.5,"x":1.921,"y":1.921}]},"晕眩ef":{"rotate":[{"time":0,"angle":0}],"translate":[{"time":0,"x":0,"y":0}],"scale":[{"time":0,"x":1,"y":1}]}}},"loop":{"slots":{"晕眩1":{"color":[{"time":0,"color":"ffffffff"}]},"晕眩2":{"color":[{"time":0,"color":"ffffffff"}]},"晕眩ADD":{"color":[{"time":0,"color":"ffffff00","curve":[0.25,0,0.75,1]},{"time":1,"color":"ffffff93"},{"time":2,"color":"ffffff00"}],"attachment":[{"time":0,"name":"晕眩"}]},"晕眩ef":{"twoColor":[{"time":0,"light":"ffffffff","dark":"000000"},{"time":1,"light":"ffffffff","dark":"544900"},{"time":2,"light":"ffffffff","dark":"000000"}]},"晕眩efAD":{"twoColor":[{"time":0,"light":"ffffffff","dark":"000000"},{"time":1,"light":"ffffffff","dark":"474300"},{"time":2,"light":"ffffffff","dark":"000000"}]}},"bones":{"晕眩1":{"rotate":[{"time":0,"angle":0}],"translate":[{"time":0,"x":0,"y":0,"curve":"stepped"},{"time":0.1667,"x":0,"y":0}],"scale":[{"time":0,"x":1,"y":1}]},"晕眩2":{"rotate":[{"time":0,"angle":0}],"translate":[{"time":0,"x":0,"y":0}],"scale":[{"time":0,"x":1,"y":1}]},"晕眩ADD":{"rotate":[{"time":0,"angle":0}],"translate":[{"time":0,"x":0,"y":0}],"scale":[{"time":0,"x":1,"y":1}]},"y":{"scale":[{"time":0,"x":1.7,"y":1.7}]},"晕眩ef":{"rotate":[{"time":0,"angle":0}],"translate":[{"time":0,"x":0,"y":0}],"scale":[{"time":0,"x":1,"y":1}]}}},"out":{"slots":{"晕眩1":{"color":[{"time":0,"color":"ffffffff"},{"time":0.1667,"color":"ffffff60","curve":[0.25,0,0.75,1]},{"time":0.6667,"color":"ffffff00"}]},"晕眩2":{"color":[{"time":0,"color":"ffffffff"},{"time":0.1667,"color":"ffffff60","curve":[0.25,0,0.75,1]},{"time":0.6667,"color":"ffffff00"}]},"晕眩ADD":{"color":[{"time":0,"color":"ffffffff","curve":[0.25,0,0.75,1]},{"time":0.6667,"color":"ffffff00"}],"attachment":[{"time":0,"name":null}]},"晕眩ef":{"twoColor":[{"time":0,"light":"ffffffff","dark":"000000"},{"time":0.6667,"light":"ffffff00","dark":"000000"}]},"晕眩efAD":{"twoColor":[{"time":0,"light":"ffffffff","dark":"000000"},{"time":0.6667,"light":"ffffff00","dark":"000000"}]}},"bones":{"晕眩1":{"rotate":[{"time":0.6667,"angle":0}],"translate":[{"time":0,"x":0,"y":0,"curve":"stepped"},{"time":0.1667,"x":0,"y":0},{"time":0.6667,"x":0,"y":4.82}],"scale":[{"time":0.6667,"x":1,"y":1}]},"晕眩2":{"rotate":[{"time":0.6667,"angle":0}],"translate":[{"time":0,"x":0,"y":0,"curve":"stepped"},{"time":0.1667,"x":0,"y":0},{"time":0.6667,"x":0,"y":-5.69}],"scale":[{"time":0.6667,"x":1,"y":1}]},"晕眩ADD":{"rotate":[{"time":0.6667,"angle":0}],"translate":[{"time":0,"x":0,"y":0,"curve":[0.25,0,0.75,1]},{"time":0.6667,"x":0,"y":4.82}],"scale":[{"time":0.6667,"x":1,"y":1}]},"y":{"rotate":[{"time":0,"angle":0}],"translate":[{"time":0,"x":0,"y":0}],"scale":[{"time":0,"x":1.791,"y":1.791}]},"晕眩ef":{"rotate":[{"time":0,"angle":0}],"translate":[{"time":0,"x":0,"y":0},{"time":0.6667,"x":0,"y":-11.8}],"scale":[{"time":0,"x":1,"y":1}]}}}}},[0]]],0,0,[0],[-1],[0]]