[[{"__type__":"cc.SceneAsset","_name":"test","scene":{"__id__":1},"asyncLoadAssets":null},{"__type__":"cc.Scene","_name":"New Node","_children":[{"__id__":2}],"_anchorPoint":{"__type__":"cc.Vec2"},"autoReleaseAssets":false},{"__type__":"cc.Node","_name":"Canvas","_parent":{"__id__":1},"_children":[{"__id__":3},{"__id__":4},{"__id__":5},{"__id__":6},{"__id__":7},{"__id__":8},{"__id__":9}],"_level":1,"_components":[{"__type__":"cc.Canvas","node":{"__id__":2}},{"__type__":"08f3f9Pjx5N+bZJdn6QAZZv","node":{"__id__":2},"tail":{"__id__":8}}],"_contentSize":{"__type__":"cc.Size","width":960,"height":640},"_position":{"__type__":"cc.Vec3","x":480,"y":320},"_id":"7fHQ1ej9BNfI4pWE9CjdYA"},{"__type__":"cc.Node","_name":"Main Camera","_parent":{"__id__":2},"_level":2,"_components":[{"__type__":"cc.Camera","node":{"__id__":3},"_clearFlags":7,"_depth":-1}]},{"__type__":"cc.Node","_name":"New Sprite(Splash)","_parent":{"__id__":2},"_level":2,"_components":[{"__type__":"cc.Sprite","node":{"__id__":4},"_materials":[{"__uuid__":"ecpdLyjvZBwrvm+cedCcQy"}],"_spriteFrame":{"__uuid__":"a2MjXRFdtLlYQ5ouAFv/+R"},"_sizeMode":0},{"__type__":"cc.Animation","node":{"__id__":4},"_clips":[{"__uuid__":"ad30z/ZwFFgISwWXqUsavw"}],"playOnLoad":true}],"_color":{"__type__":"cc.Color","r":1,"g":1,"b":1},"_contentSize":{"__type__":"cc.Size","width":100,"height":100},"_position":{"__type__":"cc.Vec3","y":172}},{"__type__":"cc.Node","_name":"New Sprite(Splash)","_parent":{"__id__":2},"_active":false,"_level":2,"_components":[{"__type__":"cc.Sprite","node":{"__id__":5},"_spriteFrame":{"__uuid__":"a2MjXRFdtLlYQ5ouAFv/+R"},"_sizeMode":0},{"__type__":"cc.Animation","node":{"__id__":5},"_defaultClip":{"__uuid__":"c9pVXsPY5BUYbA2t1phFi9"},"_clips":[{"__uuid__":"c9pVXsPY5BUYbA2t1phFi9"}],"playOnLoad":true}],"_color":{"__type__":"cc.Color","r":253,"g":244,"b":244},"_contentSize":{"__type__":"cc.Size","width":100,"height":100},"_position":{"__type__":"cc.Vec3","y":-152}},{"__type__":"cc.Node","_name":"New Sprite(Splash)","_parent":{"__id__":2},"_active":false,"_level":2,"_components":[{"__type__":"cc.Sprite","node":{"__id__":6},"_sizeMode":2},{"__type__":"10fa9noqZpH3pYATAmeKpIH","node":{"__id__":6},"playTimes":5,"row":1,"col":5,"autoDestroy":true}],"_contentSize":{"__type__":"cc.Size","width":307,"height":307},"_position":{"__type__":"cc.Vec3","x":-223}},{"__type__":"cc.Node","_name":"3","_parent":{"__id__":2},"_active":false,"_level":2,"_components":[{"__type__":"cc.Sprite","node":{"__id__":7}}],"_contentSize":{"__type__":"cc.Size","width":307,"height":307},"_position":{"__type__":"cc.Vec3","x":225}},{"__type__":"cc.Node","_name":"New Node","_parent":{"__id__":2},"_level":2,"_components":[{"__type__":"cc.MotionStreak","node":{"__id__":8},"_materials":[{"__uuid__":"ecpdLyjvZBwrvm+cedCcQy"}],"_minSeg":0,"_texture":{"__uuid__":"eaEZsKXElDGYJ/sJTBkk/d"}}],"_position":{"__type__":"cc.Vec3","x":-400}},{"__type__":"cc.Node","_name":"Tail","_parent":{"__id__":2},"_level":2,"_components":[{"__type__":"cc.MotionStreak","node":{"__id__":9},"_materials":[{"__uuid__":"ecpdLyjvZBwrvm+cedCcQy"}],"_fadeTime":0.65,"_stroke":200,"_texture":{"__uuid__":"eaEZsKXElDGYJ/sJTBkk/d"}}],"_position":{"__type__":"cc.Vec3","x":26}}],{"__type__":"cc.SpriteFrame","content":{"name":"default_sprite_splash","texture":"02delMVqdBD70a/HSD99FK","rect":[0,0,2,2],"offset":[0,0],"originalSize":[2,2],"capInsets":[0,0,0,0]}}]