[1,["b1Ls0AnstDL5xjmADQymsN"],["_texture"],[["dragonBones.DragonBonesAtlasAsset",["_name","_atlasJson"],1]],[[0,0,1,3]],[[0,"donghua_tex","{\"imagePath\":\"donghua_tex.png\",\"name\":\"donghua_tex\",\"SubTexture\":[{\"width\":127,\"y\":398,\"height\":16,\"name\":\"ying\",\"x\":50},{\"width\":51,\"y\":398,\"height\":41,\"name\":\"2_8\",\"x\":179},{\"width\":54,\"y\":416,\"height\":35,\"name\":\"2_7\",\"x\":50},{\"width\":76,\"y\":145,\"height\":64,\"name\":\"2_6\",\"x\":166},{\"width\":74,\"y\":280,\"height\":32,\"name\":\"2_5\",\"x\":177},{\"width\":71,\"y\":72,\"height\":64,\"name\":\"2_4\",\"x\":178},{\"width\":175,\"y\":1,\"height\":142,\"name\":\"2_3\",\"x\":1},{\"width\":38,\"y\":416,\"height\":35,\"name\":\"2_2\",\"x\":106},{\"width\":19,\"y\":416,\"height\":20,\"name\":\"2_1\",\"x\":146},{\"width\":68,\"y\":1,\"height\":69,\"name\":\"1_11\",\"x\":178},{\"width\":81,\"y\":284,\"height\":65,\"name\":\"1_10\",\"x\":94},{\"width\":51,\"y\":349,\"height\":41,\"name\":\"1_9\",\"x\":189},{\"width\":93,\"y\":351,\"height\":45,\"name\":\"1_8\",\"x\":94},{\"width\":71,\"y\":211,\"height\":67,\"name\":\"1_7\",\"x\":166},{\"width\":163,\"y\":145,\"height\":137,\"name\":\"1_6\",\"x\":1},{\"width\":91,\"y\":284,\"height\":95,\"name\":\"1_5\",\"x\":1},{\"width\":71,\"y\":314,\"height\":33,\"name\":\"1_4\",\"x\":177},{\"width\":45,\"y\":432,\"height\":42,\"name\":\"1_3\",\"x\":1},{\"width\":47,\"y\":381,\"height\":49,\"name\":\"1_2\",\"x\":1},{\"width\":34,\"y\":441,\"height\":27,\"name\":\"1_1\",\"x\":146}],\"width\":256,\"height\":512,\"texUUid\":{\"__uuid__\":\"b1Ls0AnstDL5xjmADQymsN\"}}"]],0,0,[0],[0],[0]]