[1,["b8h2/vvpNJ9J0Eq5jtVpGu"],0,[["sp.SkeletonData",["_name","_atlasText","textureNames","_skeletonJson","textures"],-1,3]],[[0,0,1,2,3,4,5]],[[0,"fabao15","\nfabao15.png\nsize: 193,233\nformat: RGBA8888\nfilter: Linear,Linear\nrepeat: none\nfabao15/jianbing\n  rotate: false\n  xy: 68, 121\n  size: 24, 71\n  orig: 24, 71\n  offset: 0, 0\n  index: -1\nfabao15/zhuzhu\n  rotate: false\n  xy: 68, 194\n  size: 13, 12\n  orig: 13, 12\n  offset: 0, 0\n  index: -1\nfabao15/jianshen\n  rotate: false\n  xy: 142, 1\n  size: 49, 162\n  orig: 49, 162\n  offset: 0, 0\n  index: -1\nfabao15/fuwen\n  rotate: false\n  xy: 94, 121\n  size: 9, 102\n  orig: 9, 102\n  offset: 0, 0\n  index: -1\nfabao15/tx\n  rotate: false\n  xy: 68, 1\n  size: 72, 118\n  orig: 72, 118\n  offset: 0, 0\n  index: -1\nfabao15/faguang\n  rotate: false\n  xy: 1, 1\n  size: 65, 230\n  orig: 65, 230\n  offset: 0, 0\n  index: -1\nfaqi10/fabao10-diandian\n  rotate: false\n  xy: 83, 203\n  size: 4, 5\n  orig: 4, 5\n  offset: 0, 0\n  index: -1\nfabao11/tx\n  rotate: false\n  xy: 83, 194\n  size: 7, 7\n  orig: 7, 7\n  offset: 0, 0\n  index: -1\n",["fabao15.png"],{"skeleton":{"width":143.41,"height":230,"fps":48,"hash":" ","name":"Armature","spine":"3.7.19"},"bones":[{"x":-2.1755,"name":"root"},{"rotation":-30,"name":"bone","parent":"root"},{"x":2.1755,"y":25.15,"rotation":-90,"name":"jianshen","parent":"bone"},{"length":17,"x":1.6255,"y":94.5,"rotation":-90.8024,"name":"jianbing","parent":"bone"},{"name":"diandian","parent":"bone"},{"x":2.9255,"y":35.7,"rotation":-90.8024,"name":"zhuzhu","parent":"bone"},{"x":-22.4245,"y":-0.75,"rotation":-90.8024,"name":"tx","parent":"bone"},{"x":2.4255,"y":52,"rotation":-90.8024,"name":"faguang","parent":"bone"},{"length":12,"x":48.25,"y":-0.5,"name":"fuwen","parent":"jianshen"},{"x":33.9926,"y":47.1807,"name":"tx1","parent":"tx"},{"x":-24.4765,"y":13.8346,"name":"tx2","parent":"diandian"},{"x":62.2641,"y":-7.0054,"scaleX":0.5,"scaleY":0.5,"name":"fabao10-diandian1111","parent":"diandian"},{"x":42.85,"y":-42,"scaleX":0.6,"scaleY":0.6,"name":"fabao10-diandian","parent":"diandian"},{"x":17.4866,"y":-0.6145,"scaleX":0.5,"scaleY":0.5,"name":"fabao10-diandian11111","parent":"diandian"},{"x":63.1681,"y":23.6398,"scaleX":0.8,"scaleY":0.8,"name":"fabao10-diandian11","parent":"diandian"},{"x":-69.9108,"y":-24.678,"scaleX":0.8,"scaleY":0.8,"name":"fabao10-diandian111","parent":"diandian"},{"x":17.3992,"y":38.4525,"scaleX":0.8,"scaleY":0.8,"name":"fabao10-diandian1","parent":"diandian"}],"slots":[{"name":"jianbing","bone":"jianbing","attachment":"fabao15/jianbing"},{"name":"zhuzhu","bone":"zhuzhu","attachment":"fabao15/zhuzhu"},{"name":"jianshen","bone":"jianshen","attachment":"fabao15/jianshen"},{"name":"fuwen","bone":"fuwen","attachment":"fabao15/fuwen"},{"name":"tx","bone":"tx1","blend":"additive","attachment":"fabao15/tx"},{"name":"faguang","bone":"faguang","blend":"additive","attachment":"fabao15/faguang"},{"name":"fabao10-diandian","bone":"fabao10-diandian","blend":"additive","attachment":"faqi10/fabao10-diandian"},{"name":"fabao10-diandian1","bone":"fabao10-diandian1","blend":"additive","attachment":"faqi10/fabao10-diandian"},{"name":"fabao10-diandian11","bone":"fabao10-diandian11","blend":"additive","attachment":"faqi10/fabao10-diandian"},{"name":"fabao10-diandian111","bone":"fabao10-diandian111","blend":"additive","attachment":"faqi10/fabao10-diandian"},{"name":"fabao10-diandian1111","bone":"fabao10-diandian1111","blend":"additive","attachment":"faqi10/fabao10-diandian"},{"name":"tx1","bone":"tx2","blend":"additive","attachment":"fabao11/tx"},{"name":"fabao10-diandian11111","bone":"fabao10-diandian11111","blend":"additive","attachment":"faqi10/fabao10-diandian"}],"skins":{"default":{"tx":{"fabao15/tx":{"name":"fabao15/tx","width":72,"height":118,"x":-9.06,"y":-24.4,"rotation":90.8}},"tx1":{"fabao11/tx":{"name":"fabao11/tx","width":7,"height":7,"x":-0.12,"y":-0.3}},"zhuzhu":{"fabao15/zhuzhu":{"name":"fabao15/zhuzhu","width":13,"height":12,"x":0.71,"y":-0.42,"rotation":90.8}},"fabao10-diandian11":{"faqi10/fabao10-diandian":{"name":"faqi10/fabao10-diandian","width":4,"height":5,"x":1.15}},"fabao10-diandian11111":{"faqi10/fabao10-diandian":{"name":"faqi10/fabao10-diandian","width":4,"height":5,"x":1.15}},"fuwen":{"fabao15/fuwen":{"name":"fabao15/fuwen","width":9,"height":102,"x":12.9,"y":0.82,"rotation":90}},"fabao10-diandian1111":{"faqi10/fabao10-diandian":{"name":"faqi10/fabao10-diandian","width":4,"height":5,"x":1.15}},"fabao10-diandian111":{"faqi10/fabao10-diandian":{"name":"faqi10/fabao10-diandian","width":4,"height":5,"x":1.15}},"faguang":{"fabao15/faguang":{"name":"fabao15/faguang","width":65,"height":230,"x":51.99,"y":0.8,"rotation":90.8}},"jianbing":{"fabao15/jianbing":{"name":"fabao15/jianbing","width":24,"height":71,"x":22.99,"y":0.7,"rotation":90.8}},"fabao10-diandian1":{"faqi10/fabao10-diandian":{"name":"faqi10/fabao10-diandian","width":4,"height":5,"x":1.15}},"fabao10-diandian":{"faqi10/fabao10-diandian":{"name":"faqi10/fabao10-diandian","width":4,"height":5,"x":1.15}},"jianshen":{"fabao15/jianshen":{"name":"fabao15/jianshen","width":49,"height":162,"x":51.15,"y":0.32,"rotation":90}}}},"animations":{"fabao1":{"bones":{"bone":{"translate":[{"time":0,"y":100.18,"curve":[0.5,0,0.5,1]},{"time":0.7292,"y":106.72,"curve":[0.5,0,0.5,1]},{"time":1.4584,"y":100.18}]},"jianbing":{"translate":[{"time":0,"x":2.22,"y":1.28,"curve":[0.5,0,0.5,1]},{"time":0.7292,"x":2.05,"y":2.89,"curve":[0.5,0,0.5,1]},{"time":1.4584,"x":2.22,"y":1.28}]},"zhuzhu":{"translate":[{"time":0,"curve":[0.5,0,0.5,1]},{"time":0.7292,"x":-0.46,"y":-2.32,"curve":[0.5,0,0.5,1]},{"time":1.4584}]},"tx":{"translate":[{"time":0,"x":6.19,"y":-22.94,"curve":[0.5,0,0.5,1]},{"time":1.4583,"x":1.65,"y":43.72}]},"tx1":{"translate":[{"time":0},{"time":1.4583,"x":0.8,"y":-1.34}],"scale":[{"time":0,"x":1,"y":1},{"time":1.4583,"x":2.39,"y":0.97}]},"diandian":{"translate":[{"time":0,"x":2.86,"y":-39.35}]},"tx2":{"translate":[{"time":0},{"time":1.4583,"y":28.85}]},"fabao10-diandian1111":{"translate":[{"time":0},{"time":1.4583,"y":24.42}]},"fabao10-diandian":{"translate":[{"time":0},{"time":1.4583,"x":-2.7,"y":66.21}]},"fabao10-diandian11111":{"translate":[{"time":0},{"time":1.4583,"x":2.29,"y":63.96}]},"fabao10-diandian11":{"translate":[{"time":0},{"time":1.4583,"x":-0.19,"y":45.24}]},"fabao10-diandian111":{"translate":[{"time":0},{"time":1.4583,"x":21.4,"y":36.94}]},"fabao10-diandian1":{"translate":[{"time":0},{"time":1.4583,"y":37.95}]}},"slots":{"tx":{"color":[{"time":0,"color":"FFFFFF00"},{"time":0.4167,"color":"FFFFFF99"},{"time":1.0417,"color":"FFFFFF7F"},{"time":1.4584,"color":"FFFFFF00"}]},"faguang":{"color":[{"time":0,"color":"FFFFFFFF","curve":[0.5,0,0.5,1]},{"time":0.7292,"color":"FFFFFF00","curve":[0.5,0,0.5,1]},{"time":1.4584,"color":"FFFFFFFF"}]},"fabao10-diandian":{"color":[{"time":0,"color":"FFFFFF00"},{"time":0.4167,"color":"FFFFFFFF"},{"time":1.0417,"color":"FFFFFFFF"},{"time":1.4584,"color":"FFFFFF00"}]},"fabao10-diandian1":{"color":[{"time":0,"color":"FFFFFF00"},{"time":0.4167,"color":"FFFFFFFF"},{"time":1.0417,"color":"FFFFFFFF"},{"time":1.4584,"color":"FFFFFF00"}]},"fabao10-diandian11":{"color":[{"time":0,"color":"FFFFFF00"},{"time":0.4167,"color":"FFFFFFFF"},{"time":1.0417,"color":"FFFFFFFF"},{"time":1.4584,"color":"FFFFFF00"}]},"fabao10-diandian111":{"color":[{"time":0,"color":"FFFFFF00"},{"time":0.4167,"color":"FFFFFFFF"},{"time":1.0417,"color":"FFFFFFFF"},{"time":1.4584,"color":"FFFFFF00"}]},"fabao10-diandian1111":{"color":[{"time":0,"color":"FFFFFF00"},{"time":0.4167,"color":"FFFFFFFF"},{"time":1.0417,"color":"FFFFFFFF"},{"time":1.4584,"color":"FFFFFF00"}]},"tx1":{"color":[{"time":0,"color":"FFFFFF00"},{"time":0.4167,"color":"FFFFFFFF"},{"time":1.0417,"color":"FFFFFFFF"},{"time":1.4584,"color":"FFFFFF00"}]},"fabao10-diandian11111":{"color":[{"time":0,"color":"FFFFFF00"},{"time":0.4167,"color":"FFFFFFFF"},{"time":1.0417,"color":"FFFFFFFF"},{"time":1.4584,"color":"FFFFFF00"}]}}},"fabao2":{"bones":{"bone":{"translate":[{"time":0,"y":3.76,"curve":[0.5,0,0.5,1]},{"time":0.7292,"y":18,"curve":[0.5,0,0.5,1]},{"time":1.4584,"y":3.76}]},"jianbing":{"translate":[{"time":0,"x":2.22,"y":1.28,"curve":[0.5,0,0.5,1]},{"time":0.7292,"x":2.05,"y":2.89,"curve":[0.5,0,0.5,1]},{"time":1.4584,"x":2.22,"y":1.28}]},"zhuzhu":{"translate":[{"time":0,"curve":[0.5,0,0.5,1]},{"time":0.7292,"x":-0.46,"y":-2.32,"curve":[0.5,0,0.5,1]},{"time":1.4584}]},"tx":{"translate":[{"time":0,"x":6.19,"y":-22.94,"curve":[0.5,0,0.5,1]},{"time":1.4583,"x":1.65,"y":43.72}]},"tx1":{"translate":[{"time":0},{"time":1.4583,"x":0.8,"y":-1.34}],"scale":[{"time":0,"x":1,"y":1},{"time":1.4583,"x":2.39,"y":0.97}]},"diandian":{"translate":[{"time":0,"x":2.86,"y":-39.35}]},"tx2":{"translate":[{"time":0},{"time":1.4583,"y":28.85}]},"fabao10-diandian1111":{"translate":[{"time":0},{"time":1.4583,"y":24.42}]},"fabao10-diandian":{"translate":[{"time":0},{"time":1.4583,"x":-2.7,"y":66.21}]},"fabao10-diandian11111":{"translate":[{"time":0},{"time":1.4583,"x":2.29,"y":63.96}]},"fabao10-diandian11":{"translate":[{"time":0},{"time":1.4583,"x":-0.19,"y":45.24}]},"fabao10-diandian111":{"translate":[{"time":0},{"time":1.4583,"x":21.4,"y":36.94}]},"fabao10-diandian1":{"translate":[{"time":0},{"time":1.4583,"y":37.95}]}},"slots":{"tx":{"color":[{"time":0,"color":"FFFFFF00"},{"time":0.4167,"color":"FFFFFF99"},{"time":1.0417,"color":"FFFFFF7F"},{"time":1.4584,"color":"FFFFFF00"}]},"faguang":{"color":[{"time":0,"color":"FFFFFFFF","curve":[0.5,0,0.5,1]},{"time":0.7292,"color":"FFFFFF00","curve":[0.5,0,0.5,1]},{"time":1.4584,"color":"FFFFFFFF"}]},"fabao10-diandian":{"color":[{"time":0,"color":"FFFFFF00"},{"time":0.4167,"color":"FFFFFFFF"},{"time":1.0417,"color":"FFFFFFFF"},{"time":1.4584,"color":"FFFFFF00"}]},"fabao10-diandian1":{"color":[{"time":0,"color":"FFFFFF00"},{"time":0.4167,"color":"FFFFFFFF"},{"time":1.0417,"color":"FFFFFFFF"},{"time":1.4584,"color":"FFFFFF00"}]},"fabao10-diandian11":{"color":[{"time":0,"color":"FFFFFF00"},{"time":0.4167,"color":"FFFFFFFF"},{"time":1.0417,"color":"FFFFFFFF"},{"time":1.4584,"color":"FFFFFF00"}]},"fabao10-diandian111":{"color":[{"time":0,"color":"FFFFFF00"},{"time":0.4167,"color":"FFFFFFFF"},{"time":1.0417,"color":"FFFFFFFF"},{"time":1.4584,"color":"FFFFFF00"}]},"fabao10-diandian1111":{"color":[{"time":0,"color":"FFFFFF00"},{"time":0.4167,"color":"FFFFFFFF"},{"time":1.0417,"color":"FFFFFFFF"},{"time":1.4584,"color":"FFFFFF00"}]},"tx1":{"color":[{"time":0,"color":"FFFFFF00"},{"time":0.4167,"color":"FFFFFFFF"},{"time":1.0417,"color":"FFFFFFFF"},{"time":1.4584,"color":"FFFFFF00"}]},"fabao10-diandian11111":{"color":[{"time":0,"color":"FFFFFF00"},{"time":0.4167,"color":"FFFFFFFF"},{"time":1.0417,"color":"FFFFFFFF"},{"time":1.4584,"color":"FFFFFF00"}]}}}}},[0]]],0,0,[0],[-1],[0]]