[1,["ecpdLyjvZBwrvm+cedCcQy","caJJV3aaxIvojG40kHwjAB","f5HuifbKFGFJ5Y8I+47DHL","93v2hzRKpIyp3BffCBCpym","58lgHY6W5KaoYP40SuE1Mz","74fiJ8We9E6Z6RyakQndCe","02COlbZOlD7ZtheFU7/897","27l9Xbro5Cfav33SXRtt9g","2bOCDKw6RIsKtUzoFb0ws8","17ZBm0LQJOY4041f68KbTw","21teQMq3RJoLzpuXfNbCMu","88B3KDgqhNBZb6mvnFOjz+","f4CM+fjDBK25WZFiDS64SZ","69aOt2Np9CnqcybcCBPqw1","7a/QZLET9IDreTiBfRn2PD","f8HRqNpV9AS7GTPxXTCgFz","4fm5ut1GpNW49x49EvHFVI","a2IMb9KZNNS5oXfHCP7Z6q","adSUKvBoVMHZ4zTXmszwgU","21s8jqFwdKLa5sDAK7A4U6","bfgQ7mo+FDGpTrBKGsO/xd","3cTHjEgy5I2bd9aiuFdZCZ","a6nsr7gNtAWI8AdcQorPsD","afmVaGmgJJ96aKHMFeOd5I","3ffLhar0VH4reX2JkqVVuc","79i+c+/VFDKJzMNN354Tto","36OX5WgfJHwa/o6j6KGUnd","8dNB5ykwFC5aAlt2usldKr","fbjf+xA0JIFIx8pWHXbnoV"],["node","_spriteFrame","_textureSetter","_parent","root","friendList","likeSKe","unlock","lock","tipBtn","dualBtn","loveLevel","pro","talkLabel","friendDesc","friendCon","friendSp","friendName","btnGet","btnCannel","btnClose","_N$content","data","_N$skeletonData"],[["cc.Node",["_name","_active","_opacity","_prefab","_contentSize","_components","_parent","_trs","_children","_color","_anchorPoint"],0,4,5,9,1,7,2,5,5],"cc.SpriteFrame",["cc.Sprite",["_type","_sizeMode","_fillRange","node","_materials","_spriteFrame"],0,1,3,6],["cc.Label",["_fontSize","_lineHeight","_styleFlags","_string","_isSystemFontUsed","_N$horizontalAlign","_N$verticalAlign","_N$overflow","_N$cacheMode","node","_materials"],-6,1,3],["cc.Widget",["_alignFlags","_originalWidth","_originalHeight","_left","_right","node"],-2,1],["cc.Node",["_name","_parent","_components","_prefab","_trs","_contentSize","_anchorPoint","_color"],2,1,2,4,7,5,5,5],["cc.Node",["_name","_parent","_components","_prefab","_contentSize","_trs","_children"],2,1,12,4,5,7,2],["cc.PrefabInfo",["fileId","root","asset"],2,1,1],["cc.ClickEvent",["_componentId","handler","target"],1,1],["cc.Prefab",["_name"],2],["a45edI+8dxAWJkwlI6lsN1Y",["goldNode","goldIcon","node","btnClose","btnCannel","btnGet","friendName","friendSp","friendCon","friendDesc","talkLabel","pro","loveLevel","dualBtn","tipBtn","lock","unlock","likeSKe","friendList"],1,1,1,1,1,1,1,1,1,1,1,1,1,1,1,1,1,1],["91fcdIYRxBK0bbIvoQydoMe",["node"],3,1],["08526eaTJpCXYM9VKuRXAnP",["zoomScale","_N$transition","node"],1,1],["cc.ScrollView",["vertical","brake","bounceDuration","_N$horizontalScrollBar","_N$verticalScrollBar","node","_N$content"],-2,1,1],["cc.Layout",["_resize","_N$layoutType","_N$paddingLeft","_N$spacingX","node","_layoutSize"],-1,1,5],["cc.BlockInputEvents",["node"],3,1],["cc.Mask",["_N$alphaThreshold","node","_materials"],2,1,3],["cc.LabelOutline",["_width","node","_color"],2,1,5],["sp.Skeleton",["defaultSkin","_preCacheMode","premultipliedAlpha","_animationName","node","_materials"],-1,1,3],["1896anh1MNKtpXpHYMe5dn5",["node","tmpNode","pageChangeEvent","renderEvent","selectedEvent"],3,1,1,4,4,4]],[[7,0,1,2,2],[0,0,6,5,3,4,7,2],[2,3,4,5,1],[0,0,6,8,5,3,4,7,2],[17,0,1,2,2],[2,3,4,1],[12,0,1,2,3],[0,0,8,5,3,4,7,2],[2,0,1,3,4,5,3],[3,3,0,1,4,2,5,6,8,9,10,9],[3,3,0,1,4,2,5,6,9,10,8],[0,0,1,6,5,3,4,7,3],[2,0,3,4,5,2],[0,0,6,5,3,9,4,7,2],[5,0,1,2,3,7,5,4,2],[11,0,1],[8,1],[9,0,2],[0,0,6,8,3,7,2],[0,0,8,5,3,4,10,2],[0,0,2,6,5,3,9,4,3],[0,0,6,8,5,3,4,10,7,2],[0,0,6,8,5,3,9,4,7,2],[0,0,1,6,8,5,3,4,7,3],[0,0,6,8,3,4,7,2],[0,0,6,5,3,4,2],[6,0,1,6,2,3,4,5,2],[6,0,1,2,3,4,5,2],[5,0,1,2,3,5,6,4,2],[5,0,1,2,3,4,2],[5,0,1,2,3,5,4,2],[4,0,5,2],[4,0,1,2,5,4],[4,0,3,4,1,2,5,6],[4,0,3,5,3],[4,0,4,5,3],[10,0,1,2,3,4,5,6,7,8,9,10,11,12,13,14,15,16,17,18,3],[7,1,2,1],[2,1,3,4,5,2],[2,0,2,3,4,5,3],[13,0,1,2,3,4,5,6,6],[14,0,1,2,3,4,5,5],[15,0,1],[16,0,1,2,2],[3,0,1,4,2,5,6,7,9,10,8],[3,3,0,1,4,2,5,6,7,9,10,9],[3,3,0,1,4,2,6,9,10,7],[3,3,0,1,2,5,7,9,10,7],[18,0,1,2,3,4,5,5],[19,0,1,2,3,4,1],[8,0,1,2,3]],[[[{"name":"lj_xy_dk","rect":[0,0,686,1016],"offset":[0,0],"originalSize":[686,1016],"capInsets":[0,0,0,0]}],[1],0,[0],[2],[3]],[[{"name":"lj_xy_txxz","rect":[0,0,138,139],"offset":[0,0],"originalSize":[138,139],"capInsets":[0,0,0,0]}],[1],0,[0],[2],[4]],[[{"name":"lj_xy_grzl","rect":[0,0,95,79],"offset":[0,0],"originalSize":[95,79],"capInsets":[0,0,0,0]}],[1],0,[0],[2],[5]],[[{"name":"lj_xy1","rect":[124,51,439,322],"offset":[11.5,-25],"originalSize":[664,374],"capInsets":[0,0,0,0]}],[1],0,[0],[2],[6]],[[{"name":"lj_xy_txdk","rect":[0,0,681,151],"offset":[0,0],"originalSize":[681,151],"capInsets":[0,0,0,0]}],[1],0,[0],[2],[7]],[[{"name":"lj_xy_sxbtn","rect":[0,0,149,62],"offset":[0,0],"originalSize":[149,62],"capInsets":[0,0,0,0]}],[1],0,[0],[2],[8]],[[{"name":"lj_xy_dhk","rect":[0,0,644,91],"offset":[0,0],"originalSize":[644,91],"capInsets":[0,0,0,0]}],[1],0,[0],[2],[9]],[[[17,"UIFriend"],[7,"UIFriend",[-20,-21],[[31,45,-2],[36,null,null,-19,-18,-17,-16,-15,-14,-13,-12,-11,-10,-9,-8,-7,-6,-5,-4,-3]],[37,-1,0],[5,750,1334],[375,667,0,0,0,0,1,1,1,1]],[3,"root",1,[-23,-24,-25,-26,-27,-28,-29,-30,-31],[[2,-22,[58],59]],[0,"10zDevpQlFEY/X+weCG5tj",1,0],[5,686,1016],[0,-38,0,0,0,0,1,1,1,1]],[18,"unlock",2,[-32,-33,-34,-35,-36],[0,"5dgnH/AoNPPprm6I4frQYi",1,0],[0,-20,0,0,0,0,1,1,1,1]],[7,"item",[-40,-41],[[2,-37,[38],39],[15,-38],[6,0.88,3,-39]],[0,"a9xswA2vlCDYe3VPko7IkT",1,0],[5,149,62],[250,0,0,0,0,0,1,1,1,0]],[3,"lj_tc_dk2",2,[-43,-44,-45,-46],[[12,1,-42,[13],14]],[0,"d8ROEvxeFB67r0mCldV9dV",1,0],[5,664,374],[0,85,0,0,0,0,1,1,1,1]],[7,"item",[-49,-50],[[5,-47,[20]],[15,-48]],[0,"c4oQWJTsNEg7cgegWpLblu",1,0],[5,117,117],[66,0,0,0,0,0,1,1,1,1]],[7,"pro",[-52,-53,-54],[[12,1,-51,[33],34]],[0,"daifd2papKyZdZo6UN2YD1",1,0],[5,474,28],[-70,-2,0,0,0,0,1,1,1,1]],[26,"New ScrollView",2,[-59],[[[12,1,-55,[22],23],[40,false,0.75,0.23,null,null,-57,-56],-58],4,4,1],[0,"56MY+51oNNWK09bB+4xcUP",1,0],[5,681,151],[0,335,0,0,0,0,1,1,1,1]],[19,"content",[6],[[41,1,1,7.5,11.5,-60,[5,124.5,75]]],[0,"8bqybLNaBF/Y+gQa715JpP",1,0],[5,124.5,75],[0,0,0.5]],[3,"lj_tc_bt3",3,[-62,-63,-64],[[5,-61,[45]]],[0,"28KNKNFp1CBaZr/lZEhdsC",1,0],[5,650,30],[0,-205,0,0,0,0,1,1,1,1]],[3,"lj_btn1_2",3,[-67],[[2,-65,[50],51],[6,0.88,3,-66]],[0,"40fdJC0FNFNa94MEfamdUL",1,0],[5,188,88],[-110,-410,0,0,0,0,1,1,1,0]],[3,"lj_btn1_3",3,[-70],[[2,-68,[53],54],[6,0.88,3,-69]],[0,"fd962oH3pP1qABNqOBWAyF",1,0],[5,188,88],[112,-410,0,0,0,0,1,1,1,0]],[20,"bg",200,1,[[38,0,-71,[0],1],[32,45,2,2,-72],[42,-73]],[0,"157cIpaFdObbwnCtRHDqpB",1,0],[4,4278190080],[5,750,1334]],[1,"lj_X",2,[[2,-74,[4],5],[6,0.88,3,-75]],[0,"e5hpo2sehCTbKMdv8cJxK2",1,0],[5,73,68],[285,460,0,0,0,0,1,1,1,0]],[21,"view",8,[9],[[43,0,-76,[21]],[33,45,15,15,240,250,-77]],[0,"80hfARfLBLPpkxhb1urbcN",1,0],[5,651,151],[0,0,0.5],[-325.5,0,0,0,0,0,1,1,1,1]],[11,"leftArrow",false,2,[[5,-78,[56]],[34,8,8,-79],[6,0.88,3,-80]],[0,"76Fjpc+JpBlqfJzcD1tXlB",1,0],[5,38,64],[-311,200,0,0,0,0,1,-1,1,0]],[11,"rightArrow",false,2,[[5,-81,[57]],[35,32,8,-82],[6,0.88,3,-83]],[0,"69KRFR3CVJ34YURO8J6I/U",1,0],[5,38,64],[311,200,0,0,0,0,1,1,1,0]],[22,"title",2,[-85],[[5,-84,[3]]],[0,"4a9PFLHlpPHpkWVoAUZvJy",1,0],[4,4294574079],[5,264,83],[0,450,0,0,0,0,1,1,1,1]],[1,"New Label",18,[[9,"仙友",96,96,false,1,1,1,1,-86,[2]],[4,6,-87,[4,4278190080]]],[0,"44TKGAeWVGDJrF96avUVaN",1,0],[5,204,132.95999999999998],[-0.5,2.5,0,0,0,0,1,0.5,0.5,1]],[3,"lj_xy_mzk",5,[-89],[[2,-88,[8],9]],[0,"2fzucmqshOAp0YR3Ca35JQ",1,0],[5,48,141],[-243,82,0,0,0,0,1,1,1,1]],[1,"lj_xy_grzl",5,[[2,-90,[10],11]],[0,"a1rNXs0cdMcrxji61s4F/x",1,0],[5,95,79],[246,113,0,0,0,0,1,1,1,1]],[23,"love",false,6,[-92],[[2,-91,[18],19]],[0,"8fyRg0J8JGF5dpHEAgXEYr",1,0],[5,61,55],[-36.812,39.046,0,0,0,0,1,0.68,0.68,1]],[1,"proLevel",22,[[10,"10",64,64,false,1,1,1,-93,[17]],[4,4,-94,[4,4278190080]]],[0,"e1G9pJdqhOI4Rk2vpC/fS2",1,0],[5,79.19,88.64],[-2,3,0,0,0,0,1,0.5,0.5,0.5]],[3,"lj_tc_dk3",2,[-96],[[8,1,0,-95,[25],26]],[0,"39h5H7ef1MnLSFWITCFcek",1,0],[5,645,90],[0,-53.805,0,0,0,0,1,1,1,1]],[24,"like",3,[7,4],[0,"f2LU/bmcFIupRmGyHz1rw4",1,0],[5,622,100],[0,-140,0,0,0,0,1,1,1,1]],[1,"proLevel",7,[[10,"10/10",44,56,false,1,1,1,-97,[29]],[4,4,-98,[4,4278190080]]],[0,"1fhtUOtMVAN5vLTCNc71JJ",1,0],[5,118.11,78.56],[0,1,0,0,0,0,1,0.5,0.5,0.5]],[3,"love",7,[-100],[[2,-99,[31],32]],[0,"076wh+KNNHRKe2ctWmKjHk",1,0],[5,61,55],[-222,2,0,0,0,0,1,1,1,1]],[27,"loveLevel",27,[[-101,[4,4,-102,[4,4278190080]]],1,4],[0,"6f1igvf3NDjagl8TTXm93n",1,0],[5,70.28999999999999,78.56],[0,1,0,0,0,0,1,0.5,0.5,0.5]],[1,"level",4,[[10,"双修",56,60,false,1,1,1,-103,[35]],[4,4,-104,[4,4278190080]]],[0,"9dCcTXMdFALJgpZejftlK/",1,0],[5,120,83.6],[-2,1,0,0,0,0,1,0.5,0.5,0.5]],[3,"skill",3,[-106],[[8,1,0,-105,[47],48]],[0,"24rjh6thFKUYlfW0oES0HA",1,0],[5,640,105],[0,-295,0,0,0,0,1,1,1,1]],[1,"New Label",11,[[9,"聊天",72,72,false,1,1,1,1,-107,[49]],[4,4,-108,[4,4278190080]]],[0,"0fj0oeqa9HWbhaLyYjH4Zx",1,0],[5,152,98.72],[-1.472,2.5,0,0,0,0,1,0.5,0.5,1]],[1,"New Label",12,[[9,"送礼",72,72,false,1,1,1,1,-109,[52]],[4,4,-110,[4,4278190080]]],[0,"7apUPgmfRM/ZLbEl8Cn5kR",1,0],[5,152,98.72],[-0.641,0.759,0,0,0,0,1,0.5,0.5,1]],[13,"lock",2,[[9,"1500层后解锁",84,84,false,1,1,1,1,-111,[55]]],[0,"60iKOhLsFH+qZAJqdcoc3S",1,0],[4,4284637794],[5,522.87,105.84],[-0.5,-280,0,0,0,0,1,0.5,0.5,1]],[28,"friendSp",5,[-112],[0,"07pPTaM3hDDYfMevq2GDBC",1,0],[5,439,322],[0,0.5,0],[3,-180,0,0,0,0,1,1,1,1]],[5,34,[6]],[14,"level",20,[-113],[0,"1c1RGYb19OT5eQnRTiq2le",1,0],[4,4281023564],[5,50,252.48],[0,1.5,0,0,0,0,1,0.5,0.5,0.5]],[44,48,48,false,1,1,1,2,36,[7]],[29,"likeSke",5,[-114],[0,"7bzxrZem5G2Z/Wxdpzqtrq",1,0],[0,30,0,0,0,0,1,1,1,1]],[48,"default",0,false,"ani1",38,[12]],[11,"light",false,6,[[2,-115,[15],16]],[0,"4e+c11CQJKQYXGepyxOg91",1,0],[5,138,139],[-3,0,0,0,0,0,1,1,1,1]],[49,8,6,[16],[50,"a45edI+8dxAWJkwlI6lsN1Y","initOrder",1],[16]],[30,"level",24,[-116],[0,"35fYkp599Pza8qMyeRb8GM",1,0],[5,1200,90.72],[0,0,0,0,0,0,1,0.5,0.5,0.5]],[45,"每次见到师兄，我都很开心。",48,72,false,1,1,1,3,42,[24]],[25,"proSp",7,[[39,3,1,-117,[27],28]],[0,"d8VHP5h0ZF/5h/klVlMAOu",1,0],[5,470,24]],[10,"10",56,56,false,1,1,1,28,[30]],[1,"red",4,[[2,-118,[36],37]],[0,"e26v1csONIa40DXZvhorzl",1,0],[5,30,30],[57,22.5,0,0,0,0,1,1,1,1]],[1,"lj_tc_bt4",10,[[8,1,0,-119,[40],41]],[0,"f1byMUEc9KZZ+W2N+ArXVT",1,0],[5,250,18],[-198,0,0,0,0,0,1,1,1,1]],[13,"swordName",10,[[46,"仙友加持",64,64,false,1,1,-120,[42]]],[0,"c90EGodiBOM5nPxzIX56o7",1,0],[4,4278190080],[5,256,80.64],[0,1,0,0,0,0,1,0.5,0.5,0.5]],[1,"lj_tc_bt4",10,[[8,1,0,-121,[43],44]],[0,"d2YGS4+pdIpIhG839+bhlP",1,0],[5,250,18],[198,0,0,0,0,0,1,-1,1,1]],[14,"desc",30,[-122],[0,"b0Pkoxnm1N+Z+jPJQgCrsw",1,0],[4,4280756007],[5,1100,75.6],[0,-5,0,0,0,0,1,0.5,0.5,1]],[47,"所有剑+2%的攻击力",60,60,1,1,3,50,[46]]],0,[0,4,1,0,0,1,0,5,41,0,6,39,0,7,3,0,8,33,0,9,21,0,10,4,0,11,45,0,12,7,0,13,43,0,14,51,0,15,9,0,16,35,0,17,37,0,18,12,0,19,11,0,20,14,0,0,1,0,-1,13,0,-2,2,0,0,2,0,-1,18,0,-2,14,0,-3,5,0,-4,8,0,-5,24,0,-6,3,0,-7,33,0,-8,16,0,-9,17,0,-1,25,0,-2,10,0,-3,30,0,-4,11,0,-5,12,0,0,4,0,0,4,0,0,4,0,-1,29,0,-2,46,0,0,5,0,-1,34,0,-2,20,0,-3,21,0,-4,38,0,0,6,0,0,6,0,-1,40,0,-2,22,0,0,7,0,-1,44,0,-2,26,0,-3,27,0,0,8,0,21,9,0,0,8,0,-3,41,0,-1,15,0,0,9,0,0,10,0,-1,47,0,-2,48,0,-3,49,0,0,11,0,0,11,0,-1,31,0,0,12,0,0,12,0,-1,32,0,0,13,0,0,13,0,0,13,0,0,14,0,0,14,0,0,15,0,0,15,0,0,16,0,0,16,0,0,16,0,0,17,0,0,17,0,0,17,0,0,18,0,-1,19,0,0,19,0,0,19,0,0,20,0,-1,36,0,0,21,0,0,22,0,-1,23,0,0,23,0,0,23,0,0,24,0,-1,42,0,0,26,0,0,26,0,0,27,0,-1,28,0,-1,45,0,0,28,0,0,29,0,0,29,0,0,30,0,-1,50,0,0,31,0,0,31,0,0,32,0,0,32,0,0,33,0,-1,35,0,-1,37,0,-1,39,0,0,40,0,-1,43,0,0,44,0,0,46,0,0,47,0,0,48,0,0,49,0,-1,51,0,22,1,4,3,25,6,3,9,7,3,25,9,3,15,122],[0,0,0,0,0,0,0,0,0,0,0,0,0,0,0,0,0,0,0,0,0,0,0,0,0,0,0,0,0,0,0,0,0,0,0,0,0,0,0,0,0,0,0,0,0,0,0,0,0,0,0,0,0,0,0,0,0,0,0,0,35,39],[-1,1,-1,-1,-1,1,-1,-1,-1,1,-1,1,-1,-1,1,-1,1,-1,-1,1,-1,-1,-1,1,-1,-1,1,-1,1,-1,-1,-1,1,-1,1,-1,-1,1,-1,1,-1,1,-1,-1,1,-1,-1,-1,1,-1,-1,1,-1,-1,1,-1,-1,-1,-1,1,1,23],[0,10,0,0,0,11,0,0,0,12,0,13,14,0,15,0,16,0,0,1,0,0,0,17,0,0,18,0,19,0,0,0,1,0,20,0,0,21,0,22,0,2,0,0,2,0,0,0,23,0,0,24,0,0,25,0,0,0,0,26,27,28]]]]