[1,["ab/0yHdbxGZZTtJ8FiUa/n"],0,[["sp.SkeletonData",["_name","_atlasText","textureNames","_skeletonJson","textures"],-1,3]],[[0,0,1,2,3,4,5]],[[0,"dujie","\ndujie.png\nsize: 1955,794\nformat: RGBA8888\nfilter: Linear,Linear\nrepeat: none\nguang\n  rotate: false\n  xy: 1501, 18\n  size: 148, 148\n  orig: 150, 150\n  offset: 1, 0\n  index: -1\nheguangsucai01\n  rotate: false\n  xy: 1548, 393\n  size: 198, 242\n  orig: 400, 400\n  offset: 106, 46\n  index: -1\nheguangsucai02\n  rotate: true\n  xy: 2, 2\n  size: 191, 237\n  orig: 400, 400\n  offset: 106, 45\n  index: -1\nheguangsucai03\n  rotate: true\n  xy: 1342, 181\n  size: 182, 222\n  orig: 400, 400\n  offset: 109, 51\n  index: -1\nheguangsucai04\n  rotate: false\n  xy: 1566, 168\n  size: 188, 223\n  orig: 400, 400\n  offset: 106, 51\n  index: -1\nheguangsucai05\n  rotate: false\n  xy: 1748, 397\n  size: 199, 238\n  orig: 400, 400\n  offset: 102, 46\n  index: -1\nheguangsucai06\n  rotate: false\n  xy: 1342, 365\n  size: 204, 243\n  orig: 400, 400\n  offset: 101, 47\n  index: -1\nheguangsucai07\n  rotate: false\n  xy: 1756, 164\n  size: 197, 231\n  orig: 400, 400\n  offset: 106, 51\n  index: -1\nheguangsucai08\n  rotate: true\n  xy: 599, 153\n  size: 181, 225\n  orig: 400, 400\n  offset: 108, 47\n  index: -1\nheguangsucai09\n  rotate: true\n  xy: 952, 84\n  size: 179, 216\n  orig: 400, 400\n  offset: 110, 53\n  index: -1\nimage1\n  rotate: true\n  xy: 808, 8\n  size: 116, 138\n  orig: 117, 139\n  offset: 1, 0\n  index: -1\nimage2\n  rotate: true\n  xy: 1818, 49\n  size: 113, 120\n  orig: 116, 122\n  offset: 1, 1\n  index: -1\nimage2_1\n  rotate: true\n  xy: 445, 18\n  size: 189, 144\n  orig: 189, 152\n  offset: 0, 0\n  index: -1\nimage2_2\n  rotate: false\n  xy: 1651, 73\n  size: 165, 89\n  orig: 165, 92\n  offset: 0, 0\n  index: -1\nimage3\n  rotate: true\n  xy: 1330, 43\n  size: 136, 169\n  orig: 139, 171\n  offset: 2, 1\n  index: -1\nimage4\n  rotate: true\n  xy: 1470, 637\n  size: 155, 479\n  orig: 159, 485\n  offset: 3, 1\n  index: -1\nimage5\n  rotate: true\n  xy: 456, 336\n  size: 242, 492\n  orig: 244, 495\n  offset: 1, 1\n  index: -1\nimage6\n  rotate: true\n  xy: 995, 610\n  size: 182, 473\n  orig: 184, 476\n  offset: 1, 1\n  index: -1\nimage8\n  rotate: true\n  xy: 456, 580\n  size: 212, 537\n  orig: 215, 543\n  offset: 1, 3\n  index: -1\nimage9\n  rotate: true\n  xy: 2, 195\n  size: 143, 378\n  orig: 145, 382\n  offset: 1, 0\n  index: -1\nleidian1\n  rotate: false\n  xy: 1470, 617\n  size: 49, 18\n  orig: 50, 18\n  offset: 1, 0\n  index: -1\nleidian2\n  rotate: false\n  xy: 948, 11\n  size: 60, 71\n  orig: 62, 73\n  offset: 1, 1\n  index: -1\nleidian3\n  rotate: false\n  xy: 1010, 23\n  size: 58, 59\n  orig: 59, 62\n  offset: 0, 1\n  index: -1\nleidian4\n  rotate: false\n  xy: 950, 530\n  size: 41, 48\n  orig: 41, 48\n  offset: 0, 0\n  index: -1\nleidian5\n  rotate: false\n  xy: 1651, 23\n  size: 39, 48\n  orig: 59, 48\n  offset: 20, 0\n  index: -1\nren\n  rotate: false\n  xy: 241, 2\n  size: 100, 191\n  orig: 100, 191\n  offset: 0, 0\n  index: -1\nren05\n  rotate: false\n  xy: 241, 2\n  size: 100, 191\n  orig: 100, 191\n  offset: 0, 0\n  index: -1\nren0\n  rotate: false\n  xy: 343, 2\n  size: 100, 191\n  orig: 100, 191\n  offset: 0, 0\n  index: -1\nren3\n  rotate: true\n  xy: 382, 209\n  size: 125, 215\n  orig: 128, 219\n  offset: 1, 2\n  index: -1\nren4\n  rotate: true\n  xy: 591, 26\n  size: 125, 215\n  orig: 128, 219\n  offset: 1, 2\n  index: -1\ntupo09\n  rotate: false\n  xy: 1170, 110\n  size: 158, 153\n  orig: 158, 153\n  offset: 0, 0\n  index: -1\nyun\n  rotate: false\n  xy: 2, 340\n  size: 452, 452\n  orig: 452, 452\n  offset: 0, 0\n  index: -1\nyun0\n  rotate: true\n  xy: 826, 126\n  size: 208, 124\n  orig: 217, 126\n  offset: 8, 1\n  index: -1\nziseguang\n  rotate: false\n  xy: 995, 265\n  size: 345, 343\n  orig: 345, 350\n  offset: 0, 0\n  index: -1\n",["dujie.png"],{"skeleton":{"hash":"GsYwoUkBZkuuGz+yySElrtkK/Iw","spine":"3.8.75","fps":60,"images":"C:\\Users\\Administrator\\Desktop\\dujie\\dujie","audio":"C:\\Users\\Administrator\\Desktop\\dujie\\dujie"},"bones":[{"name":"root"},{"name":"image2_1_1","parent":"root","rotation":90},{"name":"image2_2_2","parent":"root"},{"name":"guang","parent":"root"},{"name":"yunyun","parent":"root"},{"name":"image1","parent":"root"},{"name":"ren","parent":"root"},{"name":"ren4","parent":"root"},{"name":"tupo09","parent":"root"},{"name":"ziseguang","parent":"root"},{"name":"ren05","parent":"root"},{"name":"leidian1","parent":"root"},{"name":"yun0","parent":"root"},{"name":"heguangsucai","parent":"root"},{"name":"yun","parent":"yunyun"},{"name":"image2_2","parent":"image2_2_2","length":1,"rotation":90},{"name":"image2_1","parent":"image2_1_1","length":1,"rotation":90},{"name":"bone","parent":"yun0","x":573.7,"y":-348.35}],"slots":[{"name":"ren4","bone":"ren4","attachment":"ren4","blend":"additive"},{"name":"ren","bone":"ren","attachment":"ren3"},{"name":"yun","bone":"yun","attachment":"yun"},{"name":"image1","bone":"image1","attachment":"image5","blend":"additive"},{"name":"guang","bone":"guang","attachment":"guang","blend":"additive"},{"name":"image2_2","bone":"image2_2","attachment":"image2_2","blend":"additive"},{"name":"image2_11","bone":"image2_1","attachment":"image2_1","blend":"additive"},{"name":"tupo09","bone":"tupo09","attachment":"tupo09","blend":"additive"},{"name":"ziseguang","bone":"ziseguang","attachment":"ziseguang","blend":"additive"},{"name":"ren05","bone":"ren05","attachment":"ren05"},{"name":"heguangsucai01","bone":"heguangsucai","attachment":"heguangsucai09"},{"name":"leidian1","bone":"leidian1","attachment":"leidian4","blend":"additive"},{"name":"yun0","bone":"yun0","attachment":"yun0"}],"skins":[{"name":"default","attachments":{"tupo09":{"tupo09":{"x":-1.66,"y":3.85,"width":158,"height":153}},"ziseguang":{"ziseguang":{"width":345,"height":350}},"yun":{"yun":{"width":452,"height":452}},"ren":{"ren":{"x":-3.58,"width":100,"height":191},"ren0":{"x":-3.58,"width":100,"height":191},"ren3":{"x":-3.58,"width":128,"height":219}},"yun0":{"yun0":{"width":217,"height":126}},"ren05":{"ren05":{"type":"mesh","hull":4,"width":100,"height":191,"uvs":[1,1,0,1,0,0,1,0],"triangles":[1,2,3,1,3,0],"vertices":[48.45,-116.94,-51.55,-116.88,-51.44,74.12,48.56,74.06],"edges":[0,2,2,4,4,6,0,6]}},"image2_11":{"image2_1":{"type":"mesh","hull":23,"width":189,"height":152,"uvs":[0.09233,0.05658,0.03413,0.12533,0.0082,0.23914,0,0.40789,0.21251,0.90838,0.72249,0.96321,0.89947,0.82796,1,0.23553,0.95185,0.10066,0.8828,0.11513,0.90185,0.27961,0.88571,0.48191,0.80132,0.64539,0.65364,0.73487,0.50899,0.75493,0.34389,0.68322,0.23362,0.55739,0.15529,0.40124,0.14894,0.23125,0.18651,0.05329,0.03873,0.68123,0.47256,0.99999,0.99999,0.5251],"triangles":[9,10,8,8,10,7,12,6,22,11,12,22,7,10,22,10,11,22,12,13,6,13,5,6,13,14,5,14,21,5,15,4,21,15,21,14,16,4,15,20,4,16,17,20,16,0,18,19,3,20,17,0,1,18,18,2,17,2,3,17,1,2,18],"vertices":[-77.05,-47.53,-88.05,-57.98,-92.95,-75.28,-94.5,-100.93,-54.3,-177.03,42.1,-185.33,75.2,-164.83,94.5,-74.73,85.4,-54.23,72.35,-57.03,75.95,-81.43,72.9,-112.18,56.95,-137.03,31.2,-150.98,1.45,-153.68,-29.45,-143.23,-50.35,-123.58,-65.15,-99.93,-66.35,-74.08,-59.25,-47.03,-87.18,-142.68,-4.86,-190.93,94.55,-118.52],"edges":[0,2,2,4,4,6,6,40,8,40,8,42,10,12,10,42,12,44,14,16,14,44,16,18,18,20,20,22,22,24,24,26,26,28,28,30,30,32,32,34,34,36,36,38,38,0,36,4,34,6,32,40,30,8,28,42,10,26,12,24,22,44,14,20]}},"image2_2":{"image2_2":{"type":"mesh","hull":22,"width":165,"height":92,"uvs":[0.1802,1,0.21921,0.7906,0.26952,0.62583,0.37141,0.50076,0.49348,0.45672,0.62727,0.48967,0.97364,0.92283,1,0.69565,0.78865,0.17982,0.66061,0.07174,0.49091,0.03319,0.21656,0.12718,0.10609,0.27947,0.03842,0.47731,0,0.70761,0.01772,1,0.01374,0.62525,0.29083,0.09304,0.72181,0.55556,0.81634,0.66409,0.92618,0.41733,0.91297,0.81746],"triangles":[20,19,7,19,21,7,21,6,7,18,19,20,8,18,20,5,18,8,9,5,8,4,5,9,10,4,9,17,3,4,17,4,10,11,12,2,17,11,3,11,2,3,12,13,2,13,1,2,14,15,0,14,0,1,16,14,1,13,16,1],"vertices":[-52.77,103.58,-46.33,122.85,-38.03,138,-21.22,149.51,-1.08,153.56,21,150.53,78.15,110.68,82.5,131.58,47.63,179.04,26.5,188.98,-1.5,192.53,-46.77,183.88,-64.99,169.87,-76.16,151.67,-82.5,130.48,-79.58,103.58,-80.23,138.06,-34.51,187.02,36.6,144.47,52.2,134.48,70.32,157.19,68.14,120.37],"edges":[0,2,2,4,4,6,6,8,8,10,10,36,12,14,12,42,14,40,16,18,16,40,18,20,20,34,22,24,22,34,24,26,26,32,28,30,28,32,36,38,38,42,30,0,2,28,2,32,4,24,6,34,20,8,18,10,16,36,38,40,14,42]}},"guang":{"guang":{"width":150,"height":150}},"leidian1":{"leidian1":{"width":50,"height":18},"leidian2":{"x":-6.08,"y":-12.5,"width":62,"height":73},"leidian3":{"x":-2.82,"y":-2.69,"width":59,"height":62},"leidian4":{"x":-0.87,"y":0.1,"width":41,"height":48},"leidian5":{"x":-10.1,"y":0.55,"width":59,"height":48}},"image1":{"image1":{"x":-11.4,"y":-16.72,"width":117,"height":139},"image2":{"width":116,"height":122},"image3":{"y":-55.68,"width":139,"height":171},"image4":{"x":-7.95,"y":-118.34,"width":159,"height":485},"image5":{"x":-14.49,"y":-142.79,"width":244,"height":495},"image6":{"x":-6.55,"y":-150.09,"width":184,"height":476},"image8":{"y":-159.48,"width":215,"height":543},"image9":{"x":-0.94,"y":-52.88,"width":145,"height":382}},"ren4":{"ren4":{"x":-3.58,"y":-2.98,"width":128,"height":219}},"heguangsucai01":{"heguangsucai01":{"width":400,"height":400},"heguangsucai02":{"width":400,"height":400},"heguangsucai03":{"width":400,"height":400},"heguangsucai04":{"width":400,"height":400},"heguangsucai05":{"width":400,"height":400},"heguangsucai06":{"width":400,"height":400},"heguangsucai07":{"width":400,"height":400},"heguangsucai08":{"width":400,"height":400},"heguangsucai09":{"width":400,"height":400}}}}],"animations":{"dujie01_chenggong":{"slots":{"yun0":{"attachment":[{"name":null}]},"heguangsucai01":{"attachment":[{"name":null}]},"ren4":{"color":[{"color":"ffffffff"},{"time":0.5833,"color":"ffffff00"},{"time":1.1667,"color":"ffffffff"}]},"image1":{"attachment":[{"name":null}]},"yun":{"attachment":[{"name":null}]},"leidian1":{"attachment":[{"name":null}]},"guang":{"attachment":[{"name":null}]},"ren05":{"attachment":[{"name":null}]}},"bones":{"ren4":{"translate":[{"y":-145.62}]},"image2_1_1":{"rotate":[{"angle":-28.86}],"translate":[{"y":-146.29}],"scale":[{"x":0.25,"y":0.5}]},"image2_1":{"rotate":[{"angle":-90},{"time":0.5833,"angle":90},{"time":1.1667,"angle":-90}]},"image2_2_2":{"rotate":[{"angle":18.57}],"translate":[{"y":-153.14}],"scale":[{"x":0.5,"y":0.25}]},"image2_2":{"rotate":[{},{"time":0.5833,"angle":180},{"time":1.1667}]},"ren":{"translate":[{"y":-145.62}]},"tupo09":{"rotate":[{},{"time":0.5833,"angle":180},{"time":1.1667}],"translate":[{"y":-179.95}],"scale":[{"x":0.2,"y":0.2}]},"ziseguang":{"translate":[{"y":-180.98}]}},"deform":{"default":{"image2_2":{"image2_2":[{},{"time":0.55,"vertices":[-36.91,-213.59,-62,-184,-73.71,-144.38,-62.6,-89.71,-59.6,-53.87,-44.62,-14.72,29.87,-18.61,11.26,-5.67,-19.36,-7.78999,-75.73,-29.50999,-100.6,-73.37,-97.87,-135.85,-85.99999,-147.02,-80.10001,-165.45,-64.38,-191.68,-36.91,-213.59,-71.35,-176.73,-95.31,-109.46,-20.92,-1.25,-5.79,-0.73,0.35,-4.05,8.61,-3.85]},{"time":0.6667,"vertices":[-29.99,-173.54,-50.37,-149.5,-59.89,-117.31,-50.86,-72.89,-48.43,-43.77,-36.25,-11.96001,24.27,-15.12,9.15,-4.61,-15.73,-6.33,-61.53,-23.97,-81.74,-59.62,-79.51999,-110.38,-69.87,-119.46,-65.08,-134.43,-52.31,-155.74,-29.99,-173.54,-57.98,-143.6,-77.44,-88.94,-17,-1.02,-4.7,-0.60001,0.28,-3.28999,7,-3.12]},{"time":0.9333,"vertices":[-13.84,-80.1,-23.25,-69,-27.64,-54.14,-23.48,-33.64,-22.35,-20.2,-16.73,-5.52,11.2,-6.98,4.22,-2.13,-7.26,-2.92,-28.4,-11.06,-37.73,-27.52,-36.7,-50.94,-32.25,-55.13,-30.04,-62.05,-24.14,-71.88,-13.84,-80.1,-26.76,-66.28,-35.74,-41.05,-7.84,-0.47,-2.17,-0.28,0.13,-1.52,3.23,-1.44]},{"time":1.1667}]},"image2_11":{"image2_1":[{"offset":32,"vertices":[-1.04,0.74,0,0,0,0,0,0,-1.04,0.74001]},{"time":0.3167,"offset":8,"vertices":[-2.66,-8.16,19.7,-13.06999,27.63,-17.5,74.31,-15.1,93.79,0.54,93.79,0.54,74.31,-15.1,57.84,-11.32,27.63,-17.5,19.7,-13.06999,9.61,-20.16,-2.66,-8.16,0,0,0,0,0,0,0,0,0,0,9.61,-20.16,57.84,-11.32]},{"time":0.55,"vertices":[-6.27,-22.71,-1.78,-12.38,0.49,-21.7,18.49,-29.46,51.3,17.34,54.09,50.73,54.11,69.16,50.06,85.92,52.27,113.27,49.79,105.89,48.12,86.87,44.45,79.95,36.83,58.6,28.84,44.83,21.92,25.42999,20.16,11.97,18.08,-0.44,6.85,-8.73,-0.74,-15.86,-8.41,-23.34,33.47,-4.58,57.16,34.57001,48.49001,90]},{"time":0.9333,"offset":4,"vertices":[1.38,-5.45,1.35,-2.92,19.17,-30.04001,29.19,-11.77,36.35,21.39999,45.33,70.13,42.02,101.77,39.33,97.94,44.78,80.14,44.2,60.53,36.33,25.43,25.91,-5.97,13.93,-24.70999,3.17,-23.48,0.58,-15.83,2.35,-6.1,1.38,-5.45,0,0,6.78,-11.73,18.53,-28.31,40.68001,50.08]},{"time":1.1667,"offset":32,"vertices":[-1.04,0.74,0,0,0,0,0,0,-1.04,0.74001]}]}}},"drawOrder":[{"time":0.2,"offsets":[{"slot":"image2_2","offset":-5}]},{"time":0.5833,"offsets":[{"slot":"image2_2","offset":-4}]},{"time":0.6167,"offsets":[{"slot":"image2_2","offset":-5}]},{"time":0.6667,"offsets":[{"slot":"image2_11","offset":-6}]},{"time":0.9833},{"time":1.05,"offsets":[{"slot":"image2_2","offset":1}]}]},"dujie01_daiji1":{"slots":{"image2_2":{"attachment":[{"name":null}]},"yun0":{"attachment":[{"name":null}]},"heguangsucai01":{"attachment":[{"name":null}]},"ren4":{"attachment":[{"name":null}]},"image1":{"attachment":[{"name":null}]},"yun":{"attachment":[{"name":null}]},"ziseguang":{"attachment":[{"name":null}]},"tupo09":{"attachment":[{"name":null}]},"image2_11":{"attachment":[{"name":null}]},"leidian1":{"attachment":[{"name":null}]},"guang":{"attachment":[{"name":null}]},"ren05":{"attachment":[{"name":null}]},"ren":{"attachment":[{"name":"ren"}]}},"bones":{"guang":{"translate":[{"y":-148.44}],"scale":[{"x":3.5,"y":3.5}]},"image1":{"translate":[{"x":-1.92,"y":652.65}],"scale":[{"x":2.5,"y":2.5}]},"ren":{"translate":[{"y":-145.62}]},"yun0":{"translate":[{"y":686.47}]}}},"dujie01_shandian":{"slots":{"image2_2":{"attachment":[{"name":null}]},"yun0":{"attachment":[{"name":null},{"time":0.7667,"name":"yun0"},{"time":1.05,"name":null},{"time":1.15,"name":"yun0"},{"time":1.3333,"name":null}]},"heguangsucai01":{"attachment":[{"name":null}]},"ren4":{"attachment":[{"name":null}]},"image1":{"attachment":[{"name":null},{"time":0.4833,"name":"image1"},{"time":0.5667,"name":"image2"},{"time":0.6667,"name":"image3"},{"time":0.7667,"name":"image4"},{"time":0.8667,"name":"image5"},{"time":0.95,"name":"image6"},{"time":1.05,"name":null},{"time":1.15,"name":"image8"},{"time":1.2333,"name":"image9"},{"time":1.3333,"name":null}]},"yun":{"attachment":[{"name":null}]},"ziseguang":{"attachment":[{"name":null}]},"tupo09":{"attachment":[{"name":null}]},"image2_11":{"attachment":[{"name":null}]},"leidian1":{"attachment":[{"name":null}]},"guang":{"color":[{"color":"ffffffff"},{"time":0.4833,"color":"ffffff00"},{"time":0.6667,"color":"ffffff7f"},{"time":0.7667,"color":"ffffffff"},{"time":1.05,"color":"ffffff00"},{"time":1.15,"color":"ffffffff"},{"time":1.2333,"color":"ffffff7a"},{"time":1.3333,"color":"ffffff00"}],"attachment":[{"name":null},{"time":0.4833,"name":"guang"}]},"ren05":{"attachment":[{"name":null}]},"ren":{"attachment":[{"name":"ren"},{"time":0.7667,"name":"ren0"},{"time":1.05,"name":"ren"},{"time":1.15,"name":"ren0"},{"time":1.2333,"name":"ren"}]}},"bones":{"guang":{"translate":[{"y":-148.44}],"scale":[{"x":3.5,"y":3.5}]},"image1":{"translate":[{"x":-1.92,"y":652.65}],"scale":[{"x":2.5,"y":2.5}]},"ren":{"translate":[{"y":-145.62}]},"yun0":{"translate":[{"y":686.47}]}}},"dujie01_shibai":{"slots":{"image2_2":{"attachment":[{"name":null}]},"yun0":{"attachment":[{"name":null}]},"heguangsucai01":{"color":[{"color":"000000ff"}],"attachment":[{"name":"heguangsucai01"},{"time":0.0667,"name":"heguangsucai02"},{"time":0.1333,"name":"heguangsucai03"},{"time":0.2,"name":"heguangsucai04"},{"time":0.2667,"name":"heguangsucai05"},{"time":0.3335,"name":"heguangsucai06"},{"time":0.4002,"name":"heguangsucai07"},{"time":0.4669,"name":"heguangsucai08"},{"time":0.5336,"name":"heguangsucai09"},{"time":0.6003,"name":"heguangsucai01"},{"time":0.667,"name":"heguangsucai02"},{"time":0.7337,"name":"heguangsucai03"},{"time":0.8004,"name":"heguangsucai04"},{"time":0.8671,"name":"heguangsucai05"},{"time":0.9338,"name":"heguangsucai06"},{"time":1.0005,"name":"heguangsucai07"},{"time":1.0838,"name":"heguangsucai08"},{"time":1.1671,"name":"heguangsucai09"}]},"ren4":{"attachment":[{"name":null}]},"image1":{"attachment":[{"name":null}]},"yun":{"attachment":[{"name":null}]},"ziseguang":{"attachment":[{"name":null}]},"tupo09":{"attachment":[{"name":null}]},"image2_11":{"attachment":[{"name":null}]},"leidian1":{"attachment":[{"name":"leidian1"},{"time":0.0833,"name":"leidian2"},{"time":0.1667,"name":"leidian3"},{"time":0.25,"name":"leidian4"},{"time":0.3333,"name":"leidian5"},{"time":0.4165,"name":"leidian1"},{"time":0.4998,"name":"leidian2"},{"time":0.5831,"name":"leidian3"},{"time":0.6664,"name":"leidian4"},{"time":0.7497,"name":"leidian5"},{"time":0.833,"name":"leidian1"},{"time":0.9163,"name":"leidian2"},{"time":0.9996,"name":"leidian3"},{"time":1.0829,"name":"leidian4"},{"time":1.1662,"name":"leidian5"}]},"guang":{"attachment":[{"name":null}]},"ren":{"attachment":[{"name":null}]}},"bones":{"ren":{"translate":[{"y":-145.62}]},"ziseguang":{"translate":[{"y":-180.98}]},"leidian1":{"translate":[{"y":-167.98}],"scale":[{"x":0.8,"y":0.8}]},"heguangsucai":{"translate":[{"y":-110.39}]},"ren05":{"translate":[{"y":-146.06}]}},"drawOrder":[{"offsets":[{"slot":"tupo09","offset":1},{"slot":"heguangsucai01","offset":1}]},{"time":0.2167,"offsets":[{"slot":"image2_2","offset":-5},{"slot":"tupo09","offset":2},{"slot":"ziseguang","offset":0},{"slot":"heguangsucai01","offset":1}]},{"time":0.25,"offsets":[{"slot":"image2_2","offset":-5},{"slot":"tupo09","offset":1},{"slot":"heguangsucai01","offset":1}]},{"time":0.6333,"offsets":[{"slot":"image2_2","offset":-4},{"slot":"ziseguang","offset":1},{"slot":"heguangsucai01","offset":1}]},{"time":0.6667,"offsets":[{"slot":"image2_2","offset":-5},{"slot":"ziseguang","offset":1},{"slot":"heguangsucai01","offset":1}]},{"time":0.7167,"offsets":[{"slot":"image2_11","offset":-6},{"slot":"tupo09","offset":2},{"slot":"ziseguang","offset":0},{"slot":"heguangsucai01","offset":1}]},{"time":0.8,"offsets":[{"slot":"image2_11","offset":-6}]},{"time":0.8333,"offsets":[{"slot":"image2_11","offset":-6},{"slot":"tupo09","offset":1},{"slot":"heguangsucai01","offset":1}]},{"time":0.8833,"offsets":[{"slot":"image2_11","offset":-6}]},{"time":0.9165,"offsets":[{"slot":"image2_11","offset":-6},{"slot":"ziseguang","offset":2},{"slot":"heguangsucai01","offset":1}]},{"time":1.0498},{"time":1.0831,"offsets":[{"slot":"ziseguang","offset":2},{"slot":"heguangsucai01","offset":1}]},{"time":1.1331,"offsets":[{"slot":"image2_2","offset":1}]},{"time":1.1664,"offsets":[{"slot":"image2_2","offset":1},{"slot":"tupo09","offset":1},{"slot":"heguangsucai01","offset":1}]}]},"dujie01_yun":{"slots":{"image2_2":{"attachment":[{"name":null}]},"yun0":{"attachment":[{"name":null}]},"heguangsucai01":{"attachment":[{"name":null}]},"ren4":{"attachment":[{"name":null}]},"image1":{"attachment":[{"name":null}]},"ziseguang":{"attachment":[{"name":null}]},"tupo09":{"attachment":[{"name":null}]},"image2_11":{"attachment":[{"name":null}]},"leidian1":{"attachment":[{"name":null}]},"guang":{"attachment":[{"name":null}]},"ren05":{"attachment":[{"name":null}]},"ren":{"attachment":[{"name":null}]}},"bones":{"image1":{"translate":[{"x":-1.92,"y":652.65}],"scale":[{"x":2.5,"y":2.5}]},"yunyun":{"rotate":[{"angle":4.94}],"scale":[{"x":2.51,"y":1.21}]},"yun":{"rotate":[{},{"time":5,"angle":180},{"time":7.9167,"angle":75},{"time":10}],"translate":[{"x":1.26,"y":30.23}]}}}}},[0]]],0,0,[0],[-1],[0]]