[1,["825u5n78xIQb2C8jjp5d0q"],0,[["sp.SkeletonData",["_name","_atlasText","textureNames","_skeletonJson","textures"],-1,3]],[[0,0,1,2,3,4,5]],[[0,"fabao26","\nfabao26.png\nsize: 503,479\nformat: RGBA8888\nfilter: Linear,Linear\nrepeat: none\nfabao26/bjg\n  rotate: false\n  xy: 1, 1\n  size: 261, 237\n  orig: 261, 237\n  offset: 0, 0\n  index: -1\nfabao26/beiingguang1\n  rotate: false\n  xy: 264, 1\n  size: 231, 195\n  orig: 231, 195\n  offset: 0, 0\n  index: -1\nfabao26/gong\n  rotate: false\n  xy: 1, 240\n  size: 178, 153\n  orig: 178, 153\n  offset: 0, 0\n  index: -1\nfabao26/faguang\n  rotate: false\n  xy: 264, 198\n  size: 188, 164\n  orig: 188, 164\n  offset: 0, 0\n  index: -1\nfaqi10/fabao10-diandian\n  rotate: false\n  xy: 497, 1\n  size: 4, 5\n  orig: 4, 5\n  offset: 0, 0\n  index: -1\ne85ca685e78c5876d4efe97e5298e9a140dc3997941fa-zY6fXa_fw658\n  rotate: false\n  xy: 181, 364\n  size: 197, 113\n  orig: 200, 113\n  offset: 0, 0\n  index: -1\n",["fabao26.png"],{"skeleton":{"width":261,"height":237.31,"fps":48,"hash":" ","name":"Armature","spine":"3.7.19"},"bones":[{"name":"root"},{"name":"bone1112","parent":"root"},{"name":"0202","parent":"root"},{"x":-0.7,"y":9.2775,"rotation":-180,"name":"diandian","parent":"0202"},{"x":-10.6,"y":63.7,"name":"e85ca685e78c5876d4efe97e5298e9a140dc3997941fa-zY6fXa_fw658","parent":"0202"},{"name":"beiingguang1","parent":"0202"},{"name":"bjg","parent":"0202"},{"name":"gong","parent":"0202"},{"name":"faguang","parent":"0202"},{"x":42.85,"y":-42,"scaleX":0.6,"scaleY":0.6,"name":"fabao10-diandian","parent":"diandian"},{"x":63.1681,"y":23.6398,"scaleX":0.8,"scaleY":0.8,"name":"fabao10-diandian11","parent":"diandian"},{"x":17.3992,"y":38.4525,"scaleX":0.8,"scaleY":0.8,"name":"fabao10-diandian1","parent":"diandian"},{"x":17.4866,"y":-0.6145,"scaleX":0.5,"scaleY":0.5,"name":"fabao10-diandian11111","parent":"diandian"},{"x":-69.9108,"y":-24.678,"scaleX":0.8,"scaleY":0.8,"name":"fabao10-diandian111","parent":"diandian"},{"x":62.2641,"y":-7.0054,"scaleX":0.5,"scaleY":0.5,"name":"fabao10-diandian1111","parent":"diandian"}],"slots":[{"name":"bjg","bone":"bjg","attachment":"fabao26/bjg"},{"name":"beiingguang1","bone":"beiingguang1","attachment":"fabao26/beiingguang1"},{"name":"gong","bone":"gong","attachment":"fabao26/gong"},{"name":"faguang","bone":"faguang","blend":"additive","attachment":"fabao26/faguang"},{"name":"fabao10-diandian","bone":"fabao10-diandian","blend":"additive","attachment":"faqi10/fabao10-diandian"},{"name":"fabao10-diandian1","bone":"fabao10-diandian1","blend":"additive","attachment":"faqi10/fabao10-diandian"},{"name":"fabao10-diandian11","bone":"fabao10-diandian11","blend":"additive","attachment":"faqi10/fabao10-diandian"},{"name":"fabao10-diandian111","bone":"fabao10-diandian111","blend":"additive","attachment":"faqi10/fabao10-diandian"},{"name":"fabao10-diandian1111","bone":"fabao10-diandian1111","blend":"additive","attachment":"faqi10/fabao10-diandian"},{"name":"fabao10-diandian11111","bone":"fabao10-diandian11111","blend":"additive","attachment":"faqi10/fabao10-diandian"},{"name":"e85ca685e78c5876d4efe97e5298e9a140dc3997941fa-zY6fXa_fw658","bone":"e85ca685e78c5876d4efe97e5298e9a140dc3997941fa-zY6fXa_fw658","blend":"additive","attachment":"e85ca685e78c5876d4efe97e5298e9a140dc3997941fa-zY6fXa_fw658"}],"skins":{"default":{"fabao10-diandian11":{"faqi10/fabao10-diandian":{"name":"faqi10/fabao10-diandian","width":4,"height":5,"x":1.15}},"bjg":{"fabao26/bjg":{"name":"fabao26/bjg","width":261,"height":237}},"fabao10-diandian1":{"faqi10/fabao10-diandian":{"name":"faqi10/fabao10-diandian","width":4,"height":5,"x":1.15}},"fabao10-diandian1111":{"faqi10/fabao10-diandian":{"name":"faqi10/fabao10-diandian","width":4,"height":5,"x":1.15}},"e85ca685e78c5876d4efe97e5298e9a140dc3997941fa-zY6fXa_fw658":{"e85ca685e78c5876d4efe97e5298e9a140dc3997941fa-zY6fXa_fw658":{"name":"e85ca685e78c5876d4efe97e5298e9a140dc3997941fa-zY6fXa_fw658","width":197,"height":113,"x":1.45,"y":-1.39}},"fabao10-diandian":{"faqi10/fabao10-diandian":{"name":"faqi10/fabao10-diandian","width":4,"height":5,"x":1.15}},"beiingguang1":{"fabao26/beiingguang1":{"name":"fabao26/beiingguang1","width":231,"height":195,"x":-5,"y":-1}},"fabao10-diandian11111":{"faqi10/fabao10-diandian":{"name":"faqi10/fabao10-diandian","width":4,"height":5,"x":1.15}},"fabao10-diandian111":{"faqi10/fabao10-diandian":{"name":"faqi10/fabao10-diandian","width":4,"height":5,"x":1.15}},"gong":{"fabao26/gong":{"name":"fabao26/gong","width":178,"height":153,"x":-0.5,"y":1}},"faguang":{"fabao26/faguang":{"name":"fabao26/faguang","width":188,"height":164,"hull":4,"type":"mesh","triangles":[1,0,3,0,2,3],"uvs":[0,0,1,0,0,1,1,1],"edges":[0,2,2,6,4,6,4,0],"vertices":[-94.5,82.5,93.5,82.5,-94.5,-81.5,93.5,-81.5]}}}},"animations":{"fabao1":{"bones":{"0202":{"translate":[{"time":0,"x":12,"y":98.92,"curve":[0.5,0,0.5,1]},{"time":0.7292,"x":12,"y":115.34,"curve":[0.5,0,0.5,1]},{"time":1.4584,"x":12,"y":98.92}]},"diandian":{"translate":[{"time":0,"x":1.09,"y":-20.56}]},"fabao10-diandian111":{"translate":[{"time":0,"x":38.99},{"time":1.4583,"x":38.43,"y":-51.49}]},"fabao10-diandian1":{"translate":[{"time":0,"x":-17.53},{"time":1.4583,"x":-16.31,"y":-71.48}]},"fabao10-diandian":{"translate":[{"time":0,"x":-17.53,"y":-18.46},{"time":1.4583,"x":-16.31,"y":-50.87}]},"fabao10-diandian11":{"translate":[{"time":0,"x":-17.53,"y":-45.66},{"time":1.4583,"x":-16.31,"y":-90.65}],"scale":[{"time":0,"x":1.25,"y":1.25}]},"fabao10-diandian1111":{"translate":[{"time":0,"x":-17.53},{"time":1.4583,"x":-16.31,"y":-85.01}]},"fabao10-diandian11111":{"translate":[{"time":0,"x":-17.53},{"time":1.4583,"x":-16.31,"y":-85.01}],"scale":[{"time":0,"x":2,"y":2}]},"e85ca685e78c5876d4efe97e5298e9a140dc3997941fa-zY6fXa_fw658":{"rotate":[{"time":0,"angle":0,"curve":[0.5,0,0.5,1]},{"time":0.7292,"angle":9.95,"curve":[0.5,0,0.5,1]},{"time":1.4584,"angle":0}],"shear":[{"time":0,"curve":[0.5,0,0.5,1]},{"time":0.7292,"curve":[0.5,0,0.5,1]},{"time":1.4584}]}},"slots":{"bjg":{"color":[{"time":0,"color":"FFFFFFCC"}]},"beiingguang1":{"color":[{"time":0,"color":"FFFFFF00"}]},"faguang":{"color":[{"time":0,"color":"FFFFFFFF","curve":[0.5,0,0.5,1]},{"time":0.7292,"color":"FFFFFF00","curve":[0.5,0,0.5,1]},{"time":1.4584,"color":"FFFFFFFF"}]},"fabao10-diandian":{"color":[{"time":0,"color":"FFFFFF00"},{"time":0.4167,"color":"FFFFFFFF"},{"time":1.0417,"color":"FFFFFFFF"},{"time":1.4584,"color":"FFFFFF00"}]},"fabao10-diandian1":{"color":[{"time":0,"color":"FFFFFF00"},{"time":0.4167,"color":"FFFFFFFF"},{"time":1.0417,"color":"FFFFFFFF"},{"time":1.4584,"color":"FFFFFF00"}]},"fabao10-diandian11":{"color":[{"time":0,"color":"FFFFFF00"},{"time":0.4167,"color":"FFFFFFFF"},{"time":1.0417,"color":"FFFFFFFF"},{"time":1.4584,"color":"FFFFFF00"}]},"fabao10-diandian111":{"color":[{"time":0,"color":"FFFFFF00"},{"time":0.4167,"color":"FFFFFFFF"},{"time":1.0417,"color":"FFFFFFFF"},{"time":1.4584,"color":"FFFFFF00"}]},"fabao10-diandian1111":{"color":[{"time":0,"color":"FFFFFF00"},{"time":0.4167,"color":"FFFFFFFF"},{"time":1.0417,"color":"FFFFFFFF"},{"time":1.4584,"color":"FFFFFF00"}]},"fabao10-diandian11111":{"color":[{"time":0,"color":"FFFFFF00"},{"time":0.4167,"color":"FFFFFFFF"},{"time":1.0417,"color":"FFFFFFFF"},{"time":1.4584,"color":"FFFFFF00"}]},"e85ca685e78c5876d4efe97e5298e9a140dc3997941fa-zY6fXa_fw658":{"color":[{"time":0,"color":"FFFFFFFF"},{"time":0.7292,"color":"FFFFFF61"},{"time":1.4584,"color":"FFFFFFFF"}]}}},"fabao2":{"bones":{"0202":{"translate":[{"time":0,"x":12,"y":-5.08,"curve":[0.5,0,0.5,1]},{"time":0.7292,"x":12,"y":10.69,"curve":[0.5,0,0.5,1]},{"time":1.4584,"x":12,"y":-5.08}]},"diandian":{"translate":[{"time":0,"x":1.09,"y":-20.56}]},"fabao10-diandian111":{"translate":[{"time":0,"x":38.99},{"time":1.4583,"x":38.43,"y":-51.49}]},"fabao10-diandian1":{"translate":[{"time":0,"x":-17.53},{"time":1.4583,"x":-16.31,"y":-71.48}]},"fabao10-diandian":{"translate":[{"time":0,"x":-17.53,"y":-18.46},{"time":1.4583,"x":-16.31,"y":-50.87}]},"fabao10-diandian11":{"translate":[{"time":0,"x":-17.53,"y":-45.66},{"time":1.4583,"x":-16.31,"y":-90.65}],"scale":[{"time":0,"x":1.25,"y":1.25}]},"fabao10-diandian1111":{"translate":[{"time":0,"x":-17.53},{"time":1.4583,"x":-16.31,"y":-85.01}]},"fabao10-diandian11111":{"translate":[{"time":0,"x":-17.53},{"time":1.4583,"x":-16.31,"y":-85.01}],"scale":[{"time":0,"x":2,"y":2}]},"e85ca685e78c5876d4efe97e5298e9a140dc3997941fa-zY6fXa_fw658":{"rotate":[{"time":0,"angle":0,"curve":[0.5,0,0.5,1]},{"time":0.7292,"angle":9.95,"curve":[0.5,0,0.5,1]},{"time":1.4584,"angle":0}],"shear":[{"time":0,"curve":[0.5,0,0.5,1]},{"time":0.7292,"curve":[0.5,0,0.5,1]},{"time":1.4584}]}},"slots":{"bjg":{"color":[{"time":0,"color":"FFFFFFCC"}]},"beiingguang1":{"color":[{"time":0,"color":"FFFFFF00"}]},"faguang":{"color":[{"time":0,"color":"FFFFFFFF","curve":[0.5,0,0.5,1]},{"time":0.7292,"color":"FFFFFF00","curve":[0.5,0,0.5,1]},{"time":1.4584,"color":"FFFFFFFF"}]},"fabao10-diandian":{"color":[{"time":0,"color":"FFFFFF00"},{"time":0.4167,"color":"FFFFFFFF"},{"time":1.0417,"color":"FFFFFFFF"},{"time":1.4584,"color":"FFFFFF00"}]},"fabao10-diandian1":{"color":[{"time":0,"color":"FFFFFF00"},{"time":0.4167,"color":"FFFFFFFF"},{"time":1.0417,"color":"FFFFFFFF"},{"time":1.4584,"color":"FFFFFF00"}]},"fabao10-diandian11":{"color":[{"time":0,"color":"FFFFFF00"},{"time":0.4167,"color":"FFFFFFFF"},{"time":1.0417,"color":"FFFFFFFF"},{"time":1.4584,"color":"FFFFFF00"}]},"fabao10-diandian111":{"color":[{"time":0,"color":"FFFFFF00"},{"time":0.4167,"color":"FFFFFFFF"},{"time":1.0417,"color":"FFFFFFFF"},{"time":1.4584,"color":"FFFFFF00"}]},"fabao10-diandian1111":{"color":[{"time":0,"color":"FFFFFF00"},{"time":0.4167,"color":"FFFFFFFF"},{"time":1.0417,"color":"FFFFFFFF"},{"time":1.4584,"color":"FFFFFF00"}]},"fabao10-diandian11111":{"color":[{"time":0,"color":"FFFFFF00"},{"time":0.4167,"color":"FFFFFFFF"},{"time":1.0417,"color":"FFFFFFFF"},{"time":1.4584,"color":"FFFFFF00"}]},"e85ca685e78c5876d4efe97e5298e9a140dc3997941fa-zY6fXa_fw658":{"color":[{"time":0,"color":"FFFFFFFF"},{"time":0.7292,"color":"FFFFFF61"},{"time":1.4584,"color":"FFFFFFFF"}]}}}}},[0]]],0,0,[0],[-1],[0]]